kids/__init__.py
kids/vcs/__init__.py
kids/vcs/git.py
kids.vcs-0.0.3.dist-info/DESCRIPTION.rst
kids.vcs-0.0.3.dist-info/LICENSE.txt
kids.vcs-0.0.3.dist-info/METADATA
kids.vcs-0.0.3.dist-info/RECORD
kids.vcs-0.0.3.dist-info/WHEEL
kids.vcs-0.0.3.dist-info/metadata.json
kids.vcs-0.0.3.dist-info/top_level.txt
